tf_quat2rot/__init__.py
tf_quat2rot/check.py
tf_quat2rot/converter.py
tf_quat2rot/generator.py
tf_quat2rot-1.1.0.dist-info/LICENSE
tf_quat2rot-1.1.0.dist-info/METADATA
tf_quat2rot-1.1.0.dist-info/WHEEL
tf_quat2rot-1.1.0.dist-info/top_level.txt
tf_quat2rot-1.1.0.dist-info/RECORD
